hcvote/__init__.py
hcvote/from_files.py
hcvote/position.py
hcvote-0.2.0.dist-info/LICENSE
hcvote-0.2.0.dist-info/METADATA
hcvote-0.2.0.dist-info/WHEEL
hcvote-0.2.0.dist-info/top_level.txt
hcvote-0.2.0.dist-info/RECORD
