Metadata-Version: 2.1
Name: hcvote
Version: 0.2.0
Summary: The Hare-Clark electoral counting system, implemented in Python.
Home-page: https://github.com/LiamBlake/hcvote
Author: Liam Blake
Author-email: 
License: GNU
Platform: UNKNOWN
License-File: LICENSE
Provides-Extra: dev
Requires-Dist: black (==21.9b0) ; extra == 'dev'
Requires-Dist: isort (==5.9.3) ; extra == 'dev'
Requires-Dist: flake8 (==4.0.1) ; extra == 'dev'
Requires-Dist: mypy (==0.910) ; extra == 'dev'
Provides-Extra: test
Requires-Dist: pytest (==6.2.5) ; extra == 'test'
Requires-Dist: pytest-cov (==3.0.0) ; extra == 'test'
